config/__init__.py
discriminator/__init__.py
discriminator/patch.py
discriminator/style.py
generator/__init__.py
generator/data.py
generator/l_ae.py
generator/l_vqae.py
generator/svae.py
generator/vqae_hybrid.py
generator/vqae_magvit2.py
generator/vqae_magvit2_official.py
generator/vqae_trans.py
generator/autoencoder/__init__.py
generator/autoencoder/codec.py
generator/magvit2/__init__.py
generator/magvit2/codec.py
generator/magvit2/common.py
generator/magvit2/hyperball.py
generator/magvit2/vqae.py
generator/vq/__init__.py
generator/vq/common.py
generator/vq/hyperball.py
generator/vq/hypercube.py
generator/vq/lfq.py
metrics/__init__.py
metrics/inception.py
metrics/perceptual.py
train/__init__.py
train/ema.py
train/lecam.py
train/lr.py
torch_genai-0.0.1.dev1.dist-info/METADATA
torch_genai-0.0.1.dev1.dist-info/WHEEL
torch_genai-0.0.1.dev1.dist-info/top_level.txt
torch_genai-0.0.1.dev1.dist-info/RECORD
